[{"_": "Message", "id": 3, "peer_id": {"_": "PeerChannel", "channel_id": 1648279264}, "date": "2022-02-27T19:18:48+00:00", "message": "\u0420\u0435\u0430\u043b\u044c\u043d\u0430\u044f \u0423\u043a\u0440\u0430\u0438\u043d\u0430\n\n\u0421\u0441\u044b\u043b\u043a\u0430 \u043d\u0430 \u0437\u0430\u043a\u0440\u044b\u0442\u044b\u0439 \u043a\u0430\u043d\u0430\u043b - https://t.me/+q-64pD3WpfE0MDYy", "out": false, "mentioned": false, "media_unread": false, "silent": true, "post": true, "from_scheduled": false, "legacy": true, "edit_hide": true, "pinned": false, "from_id": null, "fwd_from": null, "via_bot_id": null, "reply_to": null, "media": null, "reply_markup": null, "entities": [{"_": "MessageEntityBold", "offset": 0, "length": 42}, {"_": "MessageEntityUrl", "offset": 45, "length": 30}], "views": 27925, "forwards": 39, "replies": null, "edit_date": "2022-02-27T20:26:46+00:00", "post_author": null, "grouped_id": null, "restriction_reason": [], "ttl_period": null}, {"_": "MessageService", "id": 1, "peer_id": {"_": "PeerChannel", "channel_id": 1648279264}, "date": "2022-02-27T19:14:19+00:00", "action": {"_": "MessageActionChannelCreate", "title": "\u0420\u0435\u0430\u043b\u044c\u043d\u0430\u044f \u0423\u043a\u0440\u0430\u0438\u043d\u0430"}, "out": false, "mentioned": false, "media_unread": false, "silent": false, "post": true, "legacy": false, "from_id": null, "reply_to": null, "ttl_period": null}]